copilotkit_history/__init__.py
copilotkit_history/endpoints.py
copilotkit_history/py.typed
copilotkit_history/types.py
copilotkit_langgraph_history-0.1.0.dist-info/METADATA
copilotkit_langgraph_history-0.1.0.dist-info/WHEEL
copilotkit_langgraph_history-0.1.0.dist-info/licenses/LICENSE
copilotkit_langgraph_history-0.1.0.dist-info/RECORD
