Metadata-Version: 2.4
Name: copilotkit-langgraph-history
Version: 0.1.0
Summary: FastAPI endpoints for CopilotKit LangGraph history persistence. Companion to the npm package copilotkit-langgraph-history.
Project-URL: Homepage, https://github.com/alakaybenjamin/copilotkit-langgraph-history-extend
Project-URL: Documentation, https://github.com/alakaybenjamin/copilotkit-langgraph-history-extend#readme
Project-URL: Repository, https://github.com/alakaybenjamin/copilotkit-langgraph-history-extend
Project-URL: Issues, https://github.com/alakaybenjamin/copilotkit-langgraph-history-extend/issues
Author: Benjamin Alaka
Maintainer: Benjamin Alaka
License-Expression: MIT
License-File: LICENSE
Keywords: ai-agent,chat-history,copilotkit,fastapi,langchain,langgraph,thread-persistence
Classifier: Development Status :: 4 - Beta
Classifier: Framework :: FastAPI
Classifier: Intended Audience :: Developers
Classifier: License :: OSI Approved :: MIT License
Classifier: Programming Language :: Python :: 3
Classifier: Programming Language :: Python :: 3.10
Classifier: Programming Language :: Python :: 3.11
Classifier: Programming Language :: Python :: 3.12
Classifier: Programming Language :: Python :: 3.13
Classifier: Topic :: Software Development :: Libraries :: Python Modules
Requires-Python: <3.14,>=3.10
Requires-Dist: fastapi>=0.100.0
Requires-Dist: langgraph>=0.2.0
Provides-Extra: dev
Requires-Dist: httpx>=0.24.0; extra == 'dev'
Requires-Dist: pytest-asyncio>=0.21.0; extra == 'dev'
Requires-Dist: pytest>=7.0.0; extra == 'dev'
